code/lec9/code114.v
/**************************************************************************/
/* code114.v                          For CSC.T341 CLD Archlab TOKYO TECH */
/**************************************************************************/
`timescale 1ns/100ps
`default_nettype none
  
module m_top ();
    reg r_clk=0; initial forever #50 r_clk = ~r_clk;
    wire [31:0] w_led;
    m_proc04 p (r_clk, w_led);
    always@(posedge r_clk) #80 $write("%4d %x %x %x %x %x\n", $time,
                          p.r_pc, p.w_ir, p.w_rrs, p.w_rrt2, p.w_rslt2);
    initial begin
        p.m_imem.cm_ram[0]={6'h0, 5'd0, 5'd0, 5'd0, 5'h0, 6'h20}; // add  $0, $0, $0
        p.m_imem.cm_ram[1]={6'h23,5'd0, 5'd4, 16'h4};             // lw   $4, 4($0)
        p.m_imem.cm_ram[2]={6'h0, 5'd1, 5'd2, 5'd5, 5'h0, 6'h20}; // add  $5, $1, $2
        p.m_imem.cm_ram[3]={6'h0, 5'd4, 5'd5, 5'd6, 5'h0, 6'h20}; // add  $6, $4, $5
        p.m_imem.cm_ram[4]={6'h8, 5'd6, 5'd8, 16'h5};             // addi $8, $6, 5
        p.m_dmem.cm_ram[0]=32'h222;
        p.m_dmem.cm_ram[1]=32'h333;
    end
    initial $dumpfile("main.vcd"); /* file name for GTKWave */
    initial $dumpvars(0, m_top);   /* module    for GTKWave */
    initial #550 $finish;
endmodule

module m_amemory (w_clk, w_addr, w_we, w_din, w_dout);
    input  wire w_clk, w_we;
    input  wire [11:0] w_addr;
    input  wire [31:0] w_din;
    output wire [31:0] w_dout;

    reg [31:0] cm_ram [0:4095]; // 4K word (4096 x 32bit) memory
    always @(posedge w_clk) if (w_we) cm_ram[w_addr] <= w_din;
    assign #20 w_dout = cm_ram[w_addr];
endmodule

module m_regfile (w_clk, w_rr1, w_rr2, w_wr, w_we, w_wdata, w_rdata1, w_rdata2);
    input  wire        w_clk;
    input  wire [4:0]  w_rr1, w_rr2, w_wr;
    input  wire [31:0] w_wdata;
    input  wire        w_we;
    output wire [31:0] w_rdata1, w_rdata2;
    
    reg [31:0] r[0:31];
    assign w_rdata1 = (w_rr1==0) ? 0 : r[w_rr1];
    assign w_rdata2 = (w_rr2==0) ? 0 : r[w_rr2];
    always @(posedge w_clk) if(w_we) r[w_wr] <= w_wdata;
    
    initial r[1] = 1;
    initial r[2] = 2;
endmodule

module m_proc04 (w_clk, w_led);
    input  wire w_clk;
    output wire [31:0] w_led;

    reg  [31:0] r_pc = 0;
    wire [31:0] w_ir, w_rrs, w_rrt, w_imm32, w_rrt2, w_rslt, w_ldd, w_rslt2;

    always @(posedge w_clk) r_pc <= #3 r_pc + 4;
    m_amemory m_imem (w_clk, r_pc[13:2], 1'd0, 32'd0, w_ir);

    wire  [5:0] w_op = w_ir[31:26];
    wire  [4:0] w_rs = w_ir[25:21];
    wire  [4:0] w_rt = w_ir[20:16];
    wire  [4:0] w_rd = w_ir[15:11];
    wire  [4:0] w_rd2 = (w_op!=0) ? w_rt : w_rd;
    wire [15:0] w_imm = w_ir[15:0];
    m_regfile m_regs (w_clk, w_rs, w_rt, w_rd2, 1'd1, w_rslt2, w_rrs, w_rrt);

    assign w_imm32 = {{16{w_imm[15]}}, w_imm};
    assign w_rrt2  = (w_op>6'h5) ? w_imm32 : w_rrt;

    assign #10 w_rslt = w_rrs + w_rrt2;

    m_amemory m_dmem (w_clk, w_rslt[13:2], 1'd0, 32'd0, w_ldd);
    assign w_rslt2 = (w_op>6'h19 && w_op<6'h28) ? w_ldd : w_rslt;

    assign w_led = w_rslt2;
endmodule

code/lec9/main.vcd
$date
	Wed May  5 16:02:21 2021
$end
$version
	Icarus Verilog
$end
$timescale
	100ps
$end
$scope module m_top $end
$var wire 32 ! w_led [31:0] $end
$var reg 1 " r_clk $end
$scope module p $end
$var wire 1 " w_clk $end
$var wire 32 # w_led [31:0] $end
$var wire 5 $ w_rt [4:0] $end
$var wire 32 % w_rslt2 [31:0] $end
$var wire 32 & w_rslt [31:0] $end
$var wire 5 ' w_rs [4:0] $end
$var wire 32 ( w_rrt2 [31:0] $end
$var wire 32 ) w_rrt [31:0] $end
$var wire 32 * w_rrs [31:0] $end
$var wire 5 + w_rd2 [4:0] $end
$var wire 5 , w_rd [4:0] $end
$var wire 6 - w_op [5:0] $end
$var wire 32 . w_ldd [31:0] $end
$var wire 32 / w_ir [31:0] $end
$var wire 32 0 w_imm32 [31:0] $end
$var wire 16 1 w_imm [15:0] $end
$var reg 32 2 r_pc [31:0] $end
$scope module m_dmem $end
$var wire 12 3 w_addr [11:0] $end
$var wire 1 " w_clk $end
$var wire 32 4 w_din [31:0] $end
$var wire 32 5 w_dout [31:0] $end
$var wire 1 6 w_we $end
$upscope $end
$scope module m_imem $end
$var wire 12 7 w_addr [11:0] $end
$var wire 1 " w_clk $end
$var wire 32 8 w_din [31:0] $end
$var wire 32 9 w_dout [31:0] $end
$var wire 1 : w_we $end
$upscope $end
$scope module m_regs $end
$var wire 1 " w_clk $end
$var wire 5 ; w_rr1 [4:0] $end
$var wire 5 < w_rr2 [4:0] $end
$var wire 32 = w_wdata [31:0] $end
$var wire 1 > w_we $end
$var wire 5 ? w_wr [4:0] $end
$var wire 32 @ w_rdata2 [31:0] $end
$var wire 32 A w_rdata1 [31:0] $end
$upscope $end
$upscope $end
$upscope $end
$enddefinitions $end
#0
$dumpvars
bx A
bx @
bx ?
1>
bx =
bx <
bx ;
0:
bx 9
b0 8
b0 7
06
bx 5
b0 4
bx 3
b0 2
bx 1
bx 0
bx /
bx .
bx -
bx ,
bx +
bx *
bx )
bx (
bx '
bx &
bx %
bx $
bx #
0"
bx !
$end
#200
b0 (
b0 )
b0 @
b0 *
b0 A
b0 +
b0 ?
b100000 0
b100000 1
b0 ,
b0 $
b0 <
b0 '
b0 ;
b0 -
b100000 /
b100000 9
#300
b0 3
b0 !
b0 #
b0 %
b0 =
b0 &
#500
b1000100010 .
b1000100010 5
1"
#530
b1 7
b100 2
#730
b1000100010 !
b1000100010 #
b1000100010 %
b1000100010 =
bx )
bx @
b100 +
b100 ?
b100 (
b100 0
b100 1
b100 $
b100 <
b100011 -
b10001100000001000000000000000100 /
b10001100000001000000000000000100 9
#830
b1 3
b100 &
#1000
0"
#1030
b1100110011 !
b1100110011 #
b1100110011 %
b1100110011 =
b1100110011 .
b1100110011 5
#1500
b1100110011 )
b1100110011 @
1"
#1530
b10 7
b1000 2
#1730
b100 !
b100 #
b100 %
b100 =
b10 )
b10 @
b1 *
b1 A
b101 +
b101 ?
b10 (
b10100000100000 0
b10100000100000 1
b101 ,
b10 $
b10 <
b1 '
b1 ;
b0 -
b1000100010100000100000 /
b1000100010100000100000 9
#1830
b0 3
b11 !
b11 #
b11 %
b11 =
b11 &
#2000
0"
#2030
b1000100010 .
b1000100010 5
#2500
1"
#2530
b11 7
b1100 2
#2730
b11 (
b110 +
b110 ?
b11 )
b11 @
b1100110011 *
b1100110011 A
b11000000100000 0
b11000000100000 1
b110 ,
b101 $
b101 <
b100 '
b100 ;
b100001010011000000100000 /
b100001010011000000100000 9
#2830
b11001101 3
b1100110110 !
b1100110110 #
b1100110110 %
b1100110110 =
b1100110110 &
#3000
0"
#3030
bx .
bx 5
#3500
1"
#3530
b100 7
b10000 2
#3730
bx )
bx @
b1100110110 *
b1100110110 A
b1000 +
b1000 ?
b101 (
b101 0
b101 1
b0 ,
b1000 $
b1000 <
b110 '
b110 ;
b1000 -
b100000110010000000000000000101 /
b100000110010000000000000000101 9
#3830
b11001110 3
b1100111011 !
b1100111011 #
b1100111011 %
b1100111011 =
b1100111011 &
#4000
0"
#4500
b1100111011 )
b1100111011 @
1"
#4530
b101 7
b10100 2
#4730
bx !
bx #
bx %
bx =
bx )
bx @
bx *
bx A
bx +
bx ?
bx (
bx 0
bx 1
bx ,
bx $
bx <
bx '
bx ;
bx -
bx /
bx 9
#4830
bx 3
bx &
