code/project6/code130.v
/**************************************************************************/
/* code130.v                          For CSC.T341 CLD Archlab TOKYO TECH */
/**************************************************************************/
`timescale 1ns/100ps
`default_nettype none

/***** top module for simulation *****/
module m_top (); 
   reg r_clk=0; initial forever #50 r_clk = ~r_clk;
   wire [31:0] w_led;

   initial $dumpfile("main.vcd");
   initial $dumpvars(0, m_top);

   m_proc08 p (r_clk, w_led);
   initial $write("time: s r_pc     w_ir     w_rrs    w_rrt2   r_rslt2  r_led\n");
   always@(posedge r_clk) $write("%4d: %d %x %x %x %x %x %x\n", $time,
                        p.r_state, p.r_pc, p.w_ir, p.w_rrs, p.w_rrt2, p.w_rslt2, w_led);
   initial #2000 $finish;
endmodule

/***** main module for FPGA implementation *****/
/*
module m_main (w_clk, w_led);
   input  wire w_clk;
   output wire [3:0] w_led;

   wire w_clk2, w_locked;
   clk_wiz_0 clk_w0 (w_clk2, 0, w_locked, w_clk);
   
   wire [31:0] w_dout;
   m_proc08 p (w_clk2, w_dout);

   vio_0 vio_00(w_clk2, w_dout);

   reg [3:0] r_led = 0;
   always @(posedge w_clk2) 
      r_led <= {^w_dout[31:24], ^w_dout[23:16], ^w_dout[15:8], ^w_dout[7:0]};
   assign w_led = r_led;
endmodule
*/

module m_amemory (w_clk, w_addr, w_we, w_din, r_dout);
   input  wire w_clk, w_we;
   input  wire [10:0] w_addr;
   input  wire [31:0] w_din;
   output reg [31:0] r_dout;
   reg [31:0] 	      cm_ram [0:2047]; // 4K word (2048 x 32bit) memory
   always @(posedge w_clk) if (w_we) cm_ram[w_addr] <= w_din;
   always @(posedge w_clk) r_dout <= cm_ram[w_addr];

`include "program.txt"
endmodule

module m_regfile (w_clk, w_rr1, w_rr2, w_wr, w_we, w_wdata, w_rdata1, w_rdata2);
   input  wire        w_clk;
   input  wire [4:0]  w_rr1, w_rr2, w_wr;
   input  wire [31:0] w_wdata;
   input  wire        w_we;
   output wire [31:0] w_rdata1, w_rdata2;

   reg [31:0] r[0:31];
   assign w_rdata1 = (w_rr1==0) ? 0 : r[w_rr1];
   assign w_rdata2 = (w_rr2==0) ? 0 : r[w_rr2];
   always @(posedge w_clk) if(w_we) r[w_wr] <= w_wdata;
   
   initial r[1] = 1;
   initial r[2] = 2;
endmodule

module m_proc08 (w_clk, r_led);
   input  wire w_clk;
   output reg [31:0] r_led;
   initial r_led = 0;
   
   reg  [31:0] r_pc = 0;
   wire [31:0] w_ir, w_rrs, w_rrt;
   wire [31:0] w_rrt2, w_rslt, w_ldd, w_rslt2;
   wire  [5:0] w_op    = w_ir[31:26];
   wire  [4:0] w_rs    = w_ir[25:21];
   wire  [4:0] w_rt    = w_ir[20:16];
   wire  [4:0] w_rd    = w_ir[15:11];
   wire [15:0] w_imm   = w_ir[15: 0];
   wire  [5:0] w_funct = w_ir[ 5: 0];

   wire w_insn_add  = (w_op==0 && w_funct==6'h20);
   wire w_insn_sllv = (w_op==0 && w_funct==6'h4);
   wire w_insn_srlv = (w_op==0 && w_funct==6'h6);
   wire w_insn_addi = (w_op==6'h8);
   wire w_insn_lw   = (w_op==6'h23);
   wire w_insn_sw   = (w_op==6'h2b);
   wire w_insn_beq  = (w_op==6'h4);
   wire w_insn_bne  = (w_op==6'h5);

   reg r_state = 0;
   always @(posedge w_clk) r_state <= r_state + 1;

   /***** first cycle IF *****/
   wire [31:0] w_pc4 = r_pc + 4;
   m_amemory m_imem (w_clk, r_pc[12:2], 1'd0, 32'd0, w_ir);
   wire w_we = w_insn_add | w_insn_addi | w_insn_sllv | w_insn_srlv | w_insn_lw;
   always @(posedge w_clk) if(r_state==4) begin
      r_pc <= #3 (r_taken) ? r_tpc : w_pc4;
      r_led <= (r_we && w_rd2==30 && r_state==1) ? w_rslt2 : r_led;
   end
   /***** second cycle ID *****/  
   wire [31:0] w_imm32 = {{16{w_imm[15]}}, w_imm};
   wire [31:0] w_tpc = w_pc4 + {w_imm32[29:0], 2'h0};
   wire  [4:0] w_rd2 = (w_insn_add | w_insn_sllv | w_insn_srlv) ? w_rd : w_rt;

   reg r_we = 0;
   m_regfile m_regs (w_clk, w_rs, w_rt, w_rd2, r_we, w_rslt2, w_rrs, w_rrt);

   reg [31:0] r_tpc = 0, r_rrs = 0, r_rrt = 0, r_rrt2 = 0, r_pc4 = 0, r_ir = 0;
   always @(posedge w_clk) if(r_state==0) begin
      r_pc4 <= w_pc4;
      r_ir <= w_ir;
      r_we <= w_we;
   end
   /***** third cycle EX *****/  
   wire w_taken = (w_insn_beq && w_rrs==w_rrt2) || (w_insn_bne && w_rrs!=w_rrt2);
   assign w_rrt2 = (w_insn_addi | w_insn_lw | w_insn_sw) ? w_imm32 : w_rrt;

   always @(posedge w_clk) if(r_state==1) begin
      r_tpc <= w_tpc;
      r_rrs <= w_rrs;
      r_rrt <= w_rrt;
      r_rrt2 <= w_rrt2;
   end
   /***** forth cycle MEM *****/  
   reg r_taken=0, r_insn_lw=0, r_insn_sw=0;
   reg [31:0] r_rslt=0;

   assign #10 w_rslt = (w_insn_sllv) ? w_rrs << w_rrt2[4:0] :
	(w_insn_srlv) ? w_rrs >> w_rrt2[4:0] : w_rrs + w_rrt2;

   m_amemory m_dmem (w_clk, r_rslt[12:2], r_insn_sw, r_rrt, w_ldd);

   always @(posedge w_clk) if(r_state==2) begin
      r_taken <= w_taken;
      r_rslt <= w_rslt;
      r_insn_lw <= w_insn_lw;
      r_insn_sw <= w_insn_sw;
   end
   /***** fifth cycle WB *****/  
   assign w_rslt2 = (r_insn_lw) ? w_ldd : r_rslt;
   reg [31:0] r_ldd = 0;

   always @(posedge w_clk) if(r_state==3) begin
      r_ldd <= w_ldd;
   end
   // どこにおくべきか不明
   // wire w_we = w_insn_add | w_insn_addi | w_insn_sllv | w_insn_srlv | w_insn_lw;
endmodule

code/project6/main.vcd
$date
	Thu May 26 23:11:52 2022
$end
$version
	Icarus Verilog
$end
$timescale
	100ps
$end
$scope module m_top $end
$var wire 32 ! w_led [31:0] $end
$var reg 1 " r_clk $end
$scope module p $end
$var wire 1 " w_clk $end
$var wire 1 # w_insn_add $end
$var wire 1 $ w_insn_sllv $end
$var wire 1 % w_insn_srlv $end
$var wire 1 & w_taken $end
$var wire 1 ' w_we $end
$var wire 32 ( w_tpc [31:0] $end
$var wire 5 ) w_rt [4:0] $end
$var wire 32 * w_rslt2 [31:0] $end
$var wire 32 + w_rslt [31:0] $end
$var wire 5 , w_rs [4:0] $end
$var wire 32 - w_rrt2 [31:0] $end
$var wire 32 . w_rrt [31:0] $end
$var wire 32 / w_rrs [31:0] $end
$var wire 5 0 w_rd2 [4:0] $end
$var wire 5 1 w_rd [4:0] $end
$var wire 32 2 w_pc4 [31:0] $end
$var wire 6 3 w_op [5:0] $end
$var wire 32 4 w_ldd [31:0] $end
$var wire 32 5 w_ir [31:0] $end
$var wire 1 6 w_insn_sw $end
$var wire 1 7 w_insn_lw $end
$var wire 1 8 w_insn_bne $end
$var wire 1 9 w_insn_beq $end
$var wire 1 : w_insn_addi $end
$var wire 32 ; w_imm32 [31:0] $end
$var wire 16 < w_imm [15:0] $end
$var wire 6 = w_funct [5:0] $end
$var reg 1 > r_insn_lw $end
$var reg 1 ? r_insn_sw $end
$var reg 32 @ r_ir [31:0] $end
$var reg 32 A r_ldd [31:0] $end
$var reg 32 B r_led [31:0] $end
$var reg 32 C r_pc [31:0] $end
$var reg 32 D r_pc4 [31:0] $end
$var reg 32 E r_rrs [31:0] $end
$var reg 32 F r_rrt [31:0] $end
$var reg 32 G r_rrt2 [31:0] $end
$var reg 32 H r_rslt [31:0] $end
$var reg 1 I r_state $end
$var reg 1 J r_taken $end
$var reg 32 K r_tpc [31:0] $end
$var reg 1 L r_we $end
$scope module m_dmem $end
$var wire 11 M w_addr [10:0] $end
$var wire 1 " w_clk $end
$var wire 32 N w_din [31:0] $end
$var wire 1 ? w_we $end
$var reg 32 O r_dout [31:0] $end
$upscope $end
$scope module m_imem $end
$var wire 11 P w_addr [10:0] $end
$var wire 1 " w_clk $end
$var wire 32 Q w_din [31:0] $end
$var wire 1 R w_we $end
$var reg 32 S r_dout [31:0] $end
$upscope $end
$scope module m_regs $end
$var wire 1 " w_clk $end
$var wire 5 T w_rr1 [4:0] $end
$var wire 5 U w_rr2 [4:0] $end
$var wire 32 V w_wdata [31:0] $end
$var wire 1 L w_we $end
$var wire 5 W w_wr [4:0] $end
$var wire 32 X w_rdata2 [31:0] $end
$var wire 32 Y w_rdata1 [31:0] $end
$upscope $end
$upscope $end
$upscope $end
$enddefinitions $end
#0
$dumpvars
bx Y
bx X
bx W
b0 V
bx U
bx T
bx S
0R
b0 Q
b0 P
bx O
b0 N
b0 M
0L
b0 K
0J
0I
b0 H
b0 G
b0 F
b0 E
b0 D
b0 C
b0 B
b0 A
b0 @
0?
0>
bx =
bx <
bx ;
x:
x9
x8
x7
x6
bx 5
bx 4
bx 3
b100 2
bx 1
bx 0
bx /
bx .
bx -
bx ,
bx +
b0 *
bx )
bx (
x'
x&
x%
x$
x#
0"
b0 !
$end
#500
1'
b1011100 (
b10110 -
0&
b10000 0
b10000 W
b0 /
b0 Y
0#
0$
0%
b10110 =
b10110 ;
b10110 <
b0 1
b10000 )
b10000 U
b0 ,
b0 T
1:
07
06
09
08
b1000 3
b100000000100000000000000010110 5
b100000000100000000000000010110 S
b100000000100000000000000010110 4
b100000000100000000000000010110 O
1I
xL
bx @
b100 D
1"
#600
b10110 +
#1000
0"
#1500
b10110 G
bx F
bx N
b1011100 K
0I
1"
#2000
0"
#2500
1I
1L
b100000000100000000000000010110 @
1"
#3000
0"
#3500
b0 .
b0 X
0I
1"
#4000
0"
#4500
1I
1"
#5000
0"
#5500
b0 F
b0 N
0I
1"
#6000
0"
#6500
1I
1"
#7000
0"
#7500
0I
1"
#8000
0"
#8500
1I
1"
#9000
0"
#9500
0I
1"
#10000
0"
#10500
1I
1"
#11000
0"
#11500
0I
1"
#12000
0"
#12500
1I
1"
#13000
0"
#13500
0I
1"
#14000
0"
#14500
1I
1"
#15000
0"
#15500
0I
1"
#16000
0"
#16500
1I
1"
#17000
0"
#17500
0I
1"
#18000
0"
#18500
1I
1"
#19000
0"
#19500
0I
1"
