code/project6/code130.v
/**************************************************************************/
/* code130.v                          For CSC.T341 CLD Archlab TOKYO TECH */
/**************************************************************************/
`timescale 1ns/100ps
`default_nettype none

/***** top module for simulation *****/
module m_top (); 
   reg r_clk=0; initial forever #50 r_clk = ~r_clk;
   wire [31:0] w_led;

   initial $dumpfile("main.vcd");
   initial $dumpvars(0, m_top);

   m_proc09 p (r_clk, w_led);
   initial $write("time: s r_pc     w_ir     w_rrs    w_rrt2   r_rslt2  r_led\n");
   always@(posedge r_clk) $write("%4d: %d %x %x %x %x %x %x\n", $time,
                        p.r_state, p.r_pc, p.w_ir, p.w_rrs, p.w_rrt2, p.w_rslt2, w_led);
   initial #2000 $finish;
endmodule

/***** main module for FPGA implementation *****/

// module m_main (w_clk, w_led);
//    input  wire w_clk;
//    output wire [3:0] w_led;

//    wire w_clk2, w_locked;
//    clk_wiz_0 clk_w0 (w_clk2, 0, w_locked, w_clk);
   
//    wire [31:0] w_dout;
//    m_proc09 p (w_clk2, w_dout);

//    vio_0 vio_00(w_clk2, w_dout);

//    reg [3:0] r_led = 0;
//    always @(posedge w_clk2) 
//       r_led <= {^w_dout[31:24], ^w_dout[23:16], ^w_dout[15:8], ^w_dout[7:0]};
//    assign w_led = r_led;
// endmodule


module m_amemory (w_clk, w_addr, w_we, w_din, w_dout);
   input  wire w_clk, w_we;
   input  wire [10:0] w_addr;
   input  wire [31:0] w_din;
   output wire [31:0] w_dout;
   reg [31:0] 	      cm_ram [0:2047]; // 4K word (2048 x 32bit) memory
   always @(posedge w_clk) if (w_we) cm_ram[w_addr] <= w_din;
   assign #20 w_dout = cm_ram[w_addr];

`include "program.txt"
endmodule

module m_regfile (w_clk, w_rr1, w_rr2, w_wr, w_we, w_wdata, w_rdata1, w_rdata2);
   input  wire        w_clk;
   input  wire [4:0]  w_rr1, w_rr2, w_wr;
   input  wire [31:0] w_wdata;
   input  wire        w_we;
   output wire [31:0] w_rdata1, w_rdata2;

   reg [31:0] r[0:31];
   assign w_rdata1 = (w_rr1==0) ? 0 : r[w_rr1];
   assign w_rdata2 = (w_rr2==0) ? 0 : r[w_rr2];
   always @(posedge w_clk) if(w_we) r[w_wr] <= w_wdata;
   
   initial r[1] = 1;
   initial r[2] = 2;
endmodule

module m_proc09 (w_clk, r_led);
   input  wire w_clk;
   output reg [31:0] r_led;
   initial r_led = 0;
   
   reg [31:0] r_pc = 0;

   wire [31:0] w_ir, w_rrs, w_rrt;
   wire [31:0] w_rrt2, w_rslt, w_ldd, w_rslt2;
   wire  [5:0] w_op    = w_ir[31:26];
   wire  [4:0] w_rs    = w_ir[25:21];
   wire  [4:0] w_rt    = w_ir[20:16];
   wire  [4:0] w_rd    = w_ir[15:11];
   wire [15:0] w_imm   = w_ir[15: 0];
   wire  [5:0] w_funct = w_ir[ 5: 0];

   wire w_insn_add  = (w_op==0 && w_funct==6'h20);
   wire w_insn_sllv = (w_op==0 && w_funct==6'h4);
   wire w_insn_srlv = (w_op==0 && w_funct==6'h6);
   wire w_insn_addi = (w_op==6'h8);
   wire w_insn_lw   = (w_op==6'h23);
   wire w_insn_sw   = (w_op==6'h2b);
   wire w_insn_beq  = (w_op==6'h4);
   wire w_insn_bne  = (w_op==6'h5);

   // 5状態を管理
   reg [3:0] r_state = 0;
   always @(posedge w_clk) begin
      if(r_state != 4'd4) r_state <= r_state + 1; 
      else r_state <= 0;
   end

   /***** first cycle IF*****/ 
   reg [31:0] w_tpc=0;

   wire [31:0] w_pc4 = r_pc + 4;
   wire w_taken = (w_insn_beq && w_rrs==w_rrt2) || (w_insn_bne && w_rrs!=w_rrt2);

   always @(posedge w_clk) if(r_state == 4'd4) begin
      r_pc <= #3 (w_taken) ? r_tpc : w_pc4;
   end

   m_amemory m_imem (w_clk, r_pc[12:2], 1'd0, 32'd0, w_ir);
   /***** second cycle ID*****/
   reg [31:0] r_ir=0, r_pc4=0; 
   wire [31:0] w_imm32 = {{16{w_imm[15]}}, w_imm};
   wire [31:0] w_tpc = w_pc4 + {w_imm32[29:0], 2'h0};
   wire  [4:0] w_rd2 = (w_insn_add | w_insn_sllv | w_insn_srlv) ? w_rd : w_rt;
   wire w_we = w_insn_add | w_insn_addi | w_insn_sllv | w_insn_srlv | w_insn_lw;

   m_regfile m_regs (w_clk, w_rs, w_rt, w_rd2, r_we, w_rslt2, w_rrs, w_rrt);
   assign w_rrt2 = (w_insn_addi | w_insn_lw | w_insn_sw) ? w_imm32 : w_rrt;

   always @(posedge w_clk) if(r_state ==  4'd0) begin
      r_ir <= w_ir;
      r_pc4 <= w_pc4;
      r_rd2 <= w_rd2;// これいる？
      r_led <= (r_we && r_rd2==30 && r_state==4) ? w_rslt2 : r_led;
   end
   /***** third cycle EX*****/
   reg [31:0] r_rrs=0, r_rrt=0, r_rrt2=0, r_tpc=0;

   assign #10 w_rslt = (w_insn_sllv) ? w_rrs << w_rrt2[4:0] :
	(w_insn_srlv) ? w_rrs >> w_rrt2[4:0] : w_rrs + w_rrt2;

   always @(posedge w_clk) if(r_state == 4'd1) begin
      r_rrs <= w_rrs;
      r_rrt <= w_rrt;
      r_rrt2 <= w_rrt2;
      r_tpc <= w_tpc;
   end
   /***** forth cycle MEM*****/   
   reg [31:0] r_rslt=0;
   reg r_taken=0;

   m_amemory m_dmem (w_clk, r_rslt[12:2], r_insn_sw, r_rrt, w_ldd);

   always @(posedge w_clk) if(r_state == 4'd2) begin
      r_rslt <= w_rslt;
      r_taken <= w_taken;
   end
   /***** fifth cycle WB*****/   
   reg r_insn_lw=0, r_insn_sw=0;

   assign w_rslt2 = (r_insn_lw) ? w_ldd : r_rslt;
   
   always @(posedge w_clk) if(r_state == 4'd3) begin
      r_insn_lw <= w_insn_lw;
      r_insn_sw <= w_insn_sw;
   end
endmodule

code/project6/main.vcd
$date
	Thu May 26 10:43:47 2022
$end
$version
	Icarus Verilog
$end
$timescale
	100ps
$end
$scope module m_top $end
$var wire 32 ! w_led [31:0] $end
$var reg 1 " r_clk $end
$scope module p $end
$var wire 1 " w_clk $end
$var wire 1 # w_insn_add $end
$var wire 1 $ w_insn_sllv $end
$var wire 1 % w_insn_srlv $end
$var wire 1 & w_taken $end
$var wire 1 ' w_we $end
$var wire 32 ( w_tpc [31:0] $end
$var wire 5 ) w_rt [4:0] $end
$var wire 32 * w_rslt2 [31:0] $end
$var wire 32 + w_rslt [31:0] $end
$var wire 5 , w_rs [4:0] $end
$var wire 32 - w_rrt2 [31:0] $end
$var wire 32 . w_rrt [31:0] $end
$var wire 32 / w_rrs [31:0] $end
$var wire 5 0 w_rd2 [4:0] $end
$var wire 5 1 w_rd [4:0] $end
$var wire 32 2 w_pc4 [31:0] $end
$var wire 6 3 w_op [5:0] $end
$var wire 32 4 w_ldd [31:0] $end
$var wire 32 5 w_ir [31:0] $end
$var wire 1 6 w_insn_sw $end
$var wire 1 7 w_insn_lw $end
$var wire 1 8 w_insn_bne $end
$var wire 1 9 w_insn_beq $end
$var wire 1 : w_insn_addi $end
$var wire 32 ; w_imm32 [31:0] $end
$var wire 16 < w_imm [15:0] $end
$var wire 6 = w_funct [5:0] $end
$var reg 1 > r_insn_lw $end
$var reg 1 ? r_insn_sw $end
$var reg 32 @ r_ir [31:0] $end
$var reg 32 A r_led [31:0] $end
$var reg 32 B r_pc [31:0] $end
$var reg 32 C r_pc4 [31:0] $end
$var reg 32 D r_rrs [31:0] $end
$var reg 32 E r_rrt [31:0] $end
$var reg 32 F r_rrt2 [31:0] $end
$var reg 32 G r_rslt [31:0] $end
$var reg 4 H r_state [3:0] $end
$var reg 1 I r_taken $end
$var reg 32 J r_tpc [31:0] $end
$var reg 1 K r_we $end
$scope module m_dmem $end
$var wire 11 L w_addr [10:0] $end
$var wire 1 " w_clk $end
$var wire 32 M w_din [31:0] $end
$var wire 32 N w_dout [31:0] $end
$var wire 1 ? w_we $end
$upscope $end
$scope module m_imem $end
$var wire 11 O w_addr [10:0] $end
$var wire 1 " w_clk $end
$var wire 32 P w_din [31:0] $end
$var wire 32 Q w_dout [31:0] $end
$var wire 1 R w_we $end
$upscope $end
$scope module m_regs $end
$var wire 1 " w_clk $end
$var wire 5 S w_rr1 [4:0] $end
$var wire 5 T w_rr2 [4:0] $end
$var wire 32 U w_wdata [31:0] $end
$var wire 1 K w_we $end
$var wire 5 V w_wr [4:0] $end
$var wire 32 W w_rdata2 [31:0] $end
$var wire 32 X w_rdata1 [31:0] $end
$upscope $end
$upscope $end
$upscope $end
$enddefinitions $end
#0
$dumpvars
bx X
bx W
bx V
b0 U
bx T
bx S
0R
bx Q
b0 P
b0 O
bx N
b0 M
b0 L
0K
b0 J
0I
b0 H
b0 G
b0 F
b0 E
b0 D
b0 C
b0 B
b0 A
b0 @
0?
0>
bx =
bx <
bx ;
x:
x9
x8
x7
x6
bx 5
bx 4
bx 3
b100 2
bx 1
bx 0
bx /
bx .
bx -
bx ,
bx +
b0 *
bx )
bx (
x'
x&
x%
x$
x#
0"
b0 !
$end
#200
1'
b1011100 (
b10110 -
0&
b10000 0
b10000 V
b0 /
b0 X
0#
0$
0%
b10110 =
b10110 ;
b10110 <
b0 1
b10000 )
b10000 T
b0 ,
b0 S
1:
07
06
09
08
b1000 3
b100000000100000000000000010110 4
b100000000100000000000000010110 N
b100000000100000000000000010110 5
b100000000100000000000000010110 Q
#300
b10110 +
#500
b1 H
b100 C
b100000000100000000000000010110 @
1"
#1000
0"
#1500
b10110 F
bx E
bx M
b1011100 J
b10 H
1"
#2000
0"
#2500
b101 L
b10110 *
b10110 U
b11 H
b10110 G
1"
#2700
b10001100001001000000000110 4
b10001100001001000000000110 N
#3000
0"
#3500
b100 H
1"
#4000
0"
#4500
b0 H
1"
#4530
b1 O
b1100000 (
b1000 2
b100 B
#4730
b1100 (
b1 -
b10001 0
b10001 V
b1 =
b1 ;
b1 <
b10001 )
b10001 T
b100000000100010000000000000001 5
b100000000100010000000000000001 Q
#4830
b1 +
#5000
0"
#5500
b1000 C
b100000000100010000000000000001 @
b1 H
1"
#6000
0"
#6500
b10 H
b1 F
b1100 J
1"
#7000
0"
#7500
b0 L
b1 *
b1 U
b1 G
b11 H
1"
#7700
b100000000100000000000000010110 4
b100000000100000000000000010110 N
#8000
0"
#8500
b100 H
1"
#9000
0"
#9500
b0 H
1"
#9530
b10 O
b10000 (
b1100 2
b1000 B
#9730
b11111111111111100100000000100100 (
bx -
b10010 0
b10010 V
bx /
bx X
1%
b110 =
b11111111111111111001000000000110 ;
b1001000000000110 <
b10010 1
b10000 )
b10000 T
b10001 ,
b10001 S
0:
b0 3
b10001100001001000000000110 5
b10001100001001000000000110 Q
#9830
bx +
#10000
0"
#10500
b1 H
b1100 C
b10001100001001000000000110 @
1"
#11000
0"
#11500
bx F
bx D
b11111111111111100100000000100100 J
b10 H
1"
#12000
0"
#12500
bx L
bx *
bx U
b11 H
bx G
1"
#12700
bx 4
bx N
#13000
0"
#13500
b100 H
1"
#14000
0"
#14500
b0 H
1"
#14530
b11 O
b11111111111111100100000000101000 (
b10000 2
b1100 B
#14730
1'
1#
0%
b11111111111111111100000010010000 (
b11110 0
b11110 V
b0 /
b0 X
b100000 =
b11111111111111111111000000100000 ;
b1111000000100000 <
b11110 1
b10010 )
b10010 T
b0 ,
b0 S
b100101111000000100000 5
b100101111000000100000 Q
#15000
0"
#15500
b10000 C
b100101111000000100000 @
b1 H
1"
#16000
0"
#16500
b10 H
b0 D
b11111111111111111100000010010000 J
1"
#17000
0"
#17500
b11 H
1"
#18000
0"
#18500
b100 H
1"
#19000
0"
#19500
b0 H
1"
#19530
b100 O
b11111111111111111100000010010100 (
b10100 2
b10000 B
#19730
b10 -
b11100 (
b10001 0
b10001 V
0#
b10 =
b10 ;
b10 <
b0 1
b10001 )
b10001 T
1:
b1000 3
b100000000100010000000000000010 5
b100000000100010000000000000010 Q
#19830
b10 +
