code/project/code120.v
/**************************************************************************/
/* code120.v                          For CSC.T341 CLD Archlab TOKYO TECH */
/**************************************************************************/
`timescale 1ns/100ps
`default_nettype none

/***** top module for simulation *****/
module m_top (); 
   reg r_clk=0; initial forever #50 r_clk = ~r_clk;
   wire [31:0] w_led;

   initial $dumpfile("main.vcd");
   initial $dumpvars(0, m_top);

   m_proc07 p (r_clk, w_led);
   initial $write("time: r_pc     w_ir     w_rrs    w_rrt2   r_rslt2  r_led\n");
   always@(posedge r_clk) $write("%4d: %x %x %x %x %x %x\n", $time,
                        p.r_pc, p.w_ir, p.w_rrs, p.w_rrt2, p.w_rslt2, w_led);
   initial #1000 $finish;
endmodule

`define HALT {6'h4, 5'd0, 5'd0, 16'hffff} // L1: beq $0, $0, L1
/***** main module for FPGA implementation *****/
// module m_main (w_clk, w_led);
//    input  wire w_clk;
//    output wire [3:0] w_led;

//    wire w_clk2, w_locked;
//    clk_wiz_0 clk_w0 (w_clk2, 0, w_locked, w_clk);

//    wire [31:0] w_dout;
//    m_proc07 p (w_clk2, w_dout);

//    vio_0 vio_00(w_clk2, w_dout);

//    reg [3:0] r_led = 0;
//    always @(posedge w_clk2) 
//      r_led <= {^w_dout[31:24], ^w_dout[23:16], ^w_dout[15:8], ^w_dout[7:0]};
//    assign w_led = r_led;
// endmodule

module m_amemory (w_clk, w_addr, w_we, w_din, w_dout);
   input  wire w_clk, w_we;
   input  wire [10:0] w_addr;
   input  wire [31:0] w_din;
   output wire [31:0] w_dout;
   reg [31:0] 	      cm_ram [0:2047]; // 4K word (2048 x 32bit) memory
   always @(posedge w_clk) if (w_we) cm_ram[w_addr] <= w_din;
   assign #20 w_dout = cm_ram[w_addr];

`include "program.txt"
endmodule

module m_regfile (w_clk, w_rr1, w_rr2, w_wr, w_we, w_wdata, w_rdata1, w_rdata2);
   input  wire        w_clk;
   input  wire [4:0]  w_rr1, w_rr2, w_wr;
   input  wire [31:0] w_wdata;
   input  wire        w_we;
   output wire [31:0] w_rdata1, w_rdata2;
   
   reg [31:0] r[0:31];
   assign w_rdata1 = (w_rr1==0) ? 0 : r[w_rr1];
   assign w_rdata2 = (w_rr2==0) ? 0 : r[w_rr2];
   always @(posedge w_clk) if(w_we) r[w_wr] <= w_wdata;
   
   initial r[1] = 1;
   initial r[2] = 2;
endmodule

module m_proc07 (w_clk, r_led);
   input  wire w_clk;
   output reg [31:0] r_led;
   initial r_led = 0;
   
   reg  [31:0] r_pc = 0;
   wire [31:0] w_ir, w_rrs, w_rrt;
   wire [31:0] w_rrt2, w_rslt, w_ldd, w_rslt2;
   wire  [5:0] w_op    = w_ir[31:26];
   wire  [4:0] w_rs    = w_ir[25:21];
   wire  [4:0] w_rt    = w_ir[20:16];
   wire  [4:0] w_rd    = w_ir[15:11];
   wire [15:0] w_imm   = w_ir[15: 0];
   wire  [5:0] w_funct = w_ir[ 5: 0];

   wire w_insn_add  = (w_op==0 && w_funct==6'h20);
   wire w_insn_sllv = (w_op==0 && w_funct==6'h4);
   wire w_insn_srlv = (w_op==0 && w_funct==6'h6);
   wire w_insn_addi = (w_op==6'h8);
   wire w_insn_lw   = (w_op==6'h23);
   wire w_insn_sw   = (w_op==6'h2b);
   wire w_insn_beq  = (w_op==6'h4);
   wire w_insn_bne  = (w_op==6'h5);
   
   wire [31:0] w_pc4 = r_pc + 4;
   wire [31:0] w_imm32 = {{16{w_imm[15]}}, w_imm};
   wire [31:0] w_tpc = w_pc4 + {w_imm32[29:0], 2'h0};
   wire w_taken = (w_insn_beq && w_rrs==w_rrt2) || (w_insn_bne && w_rrs!=w_rrt2);
   always @(posedge w_clk) r_pc <= #3 (w_taken) ? w_tpc : w_pc4;
   
   m_amemory m_imem (w_clk, r_pc[12:2], 1'd0, 32'd0, w_ir);

   wire  [4:0] w_rd2 = (w_insn_add | w_insn_sllv | w_insn_srlv) ? w_rd : w_rt;
   wire w_we = w_insn_add | w_insn_addi | w_insn_sllv | w_insn_srlv | w_insn_lw;

   m_regfile m_regs (w_clk, w_rs, w_rt, w_rd2, w_we, w_rslt2, w_rrs, w_rrt);

   assign w_rrt2 = (w_insn_addi | w_insn_lw | w_insn_sw) ? w_imm32 : w_rrt;

   assign #10 w_rslt = (w_insn_sllv) ? w_rrs << w_rrt2[4:0] :
	(w_insn_srlv) ? w_rrs >> w_rrt2[4:0] : w_rrs + w_rrt2;

   m_amemory m_dmem (w_clk, w_rslt[12:2], w_insn_sw, w_rrt, w_ldd);
   
   assign w_rslt2 = (w_insn_lw) ? w_ldd : w_rslt;

   always @(posedge w_clk) r_led <= (w_we && w_rd2==30) ? w_rslt2 : r_led;
   // always @(posedge w_clk) if(p.w_if == `HALT) $finish();
endmodule

code/project/main.vcd
$date
	Thu May 26 01:26:14 2022
$end
$version
	Icarus Verilog
$end
$timescale
	100ps
$end
$scope module m_top $end
$var wire 32 ! w_led [31:0] $end
$var reg 1 " r_clk $end
$scope module p $end
$var wire 1 " w_clk $end
$var wire 1 # w_insn_add $end
$var wire 1 $ w_insn_sllv $end
$var wire 1 % w_insn_srlv $end
$var wire 1 & w_taken $end
$var wire 1 ' w_we $end
$var wire 32 ( w_tpc [31:0] $end
$var wire 5 ) w_rt [4:0] $end
$var wire 32 * w_rslt2 [31:0] $end
$var wire 32 + w_rslt [31:0] $end
$var wire 5 , w_rs [4:0] $end
$var wire 32 - w_rrt2 [31:0] $end
$var wire 32 . w_rrt [31:0] $end
$var wire 32 / w_rrs [31:0] $end
$var wire 5 0 w_rd2 [4:0] $end
$var wire 5 1 w_rd [4:0] $end
$var wire 32 2 w_pc4 [31:0] $end
$var wire 6 3 w_op [5:0] $end
$var wire 32 4 w_ldd [31:0] $end
$var wire 32 5 w_ir [31:0] $end
$var wire 1 6 w_insn_sw $end
$var wire 1 7 w_insn_lw $end
$var wire 1 8 w_insn_bne $end
$var wire 1 9 w_insn_beq $end
$var wire 1 : w_insn_addi $end
$var wire 32 ; w_imm32 [31:0] $end
$var wire 16 < w_imm [15:0] $end
$var wire 6 = w_funct [5:0] $end
$var reg 32 > r_led [31:0] $end
$var reg 32 ? r_pc [31:0] $end
$scope module m_dmem $end
$var wire 11 @ w_addr [10:0] $end
$var wire 1 " w_clk $end
$var wire 32 A w_dout [31:0] $end
$var wire 1 6 w_we $end
$var wire 32 B w_din [31:0] $end
$upscope $end
$scope module m_imem $end
$var wire 11 C w_addr [10:0] $end
$var wire 1 " w_clk $end
$var wire 32 D w_din [31:0] $end
$var wire 32 E w_dout [31:0] $end
$var wire 1 F w_we $end
$upscope $end
$scope module m_regs $end
$var wire 1 " w_clk $end
$var wire 5 G w_rr1 [4:0] $end
$var wire 5 H w_rr2 [4:0] $end
$var wire 32 I w_wdata [31:0] $end
$var wire 1 ' w_we $end
$var wire 5 J w_wr [4:0] $end
$var wire 32 K w_rdata2 [31:0] $end
$var wire 32 L w_rdata1 [31:0] $end
$upscope $end
$upscope $end
$upscope $end
$enddefinitions $end
#0
$dumpvars
bx L
bx K
bx J
bx I
bx H
bx G
0F
bx E
b0 D
b0 C
bx B
bx A
bx @
b0 ?
b0 >
bx =
bx <
bx ;
x:
x9
x8
x7
x6
bx 5
bx 4
bx 3
b100 2
bx 1
bx 0
bx /
bx .
bx -
bx ,
bx +
bx *
bx )
bx (
x'
x&
x%
x$
x#
0"
b0 !
$end
#200
1'
b1011100 (
b10110 -
0&
b10000 0
b10000 J
b0 /
b0 L
0#
0$
0%
b10110 =
b10110 ;
b10110 <
b0 1
b10000 )
b10000 H
b0 ,
b0 G
1:
07
06
09
08
b1000 3
b100000000100000000000000010110 5
b100000000100000000000000010110 E
#300
b101 @
b10110 *
b10110 I
b10110 +
#500
b10110 .
b10110 B
b10110 K
b10001100001001000000000110 4
b10001100001001000000000110 A
1"
#530
b1 C
b1100000 (
b1000 2
b100 ?
#730
b1100 (
b1 -
b10001 0
b10001 J
bx .
bx B
bx K
b1 =
b1 ;
b1 <
b10001 )
b10001 H
b100000000100010000000000000001 5
b100000000100010000000000000001 E
#830
b0 @
b1 *
b1 I
b1 +
#1000
0"
#1030
b100000000100000000000000010110 4
b100000000100000000000000010110 A
#1500
b1 .
b1 B
b1 K
1"
#1530
b10 C
b10000 (
b1100 2
b1000 ?
#1730
b11111111111111100100000000100100 (
b10110 -
b10010 0
b10010 J
b10110 .
b10110 B
b10110 K
b1 /
b1 L
1%
b110 =
b11111111111111111001000000000110 ;
b1001000000000110 <
b10010 1
b10000 )
b10000 H
b10001 ,
b10001 G
0:
b0 3
b10001100001001000000000110 5
b10001100001001000000000110 E
#1830
b0 *
b0 I
b0 +
#2000
0"
#2500
1"
#2530
b11 C
b11111111111111100100000000101000 (
b10000 2
b1100 ?
#2730
1'
b0 -
1#
0%
b11111111111111111100000010010000 (
b11110 0
b11110 J
b0 .
b0 B
b0 K
b0 /
b0 L
b100000 =
b11111111111111111111000000100000 ;
b1111000000100000 <
b11110 1
b10010 )
b10010 H
b0 ,
b0 G
b100101111000000100000 5
b100101111000000100000 E
#3000
0"
#3500
1"
#3530
b100 C
b11111111111111111100000010010100 (
b10100 2
b10000 ?
#3730
b10 -
b11100 (
b10001 0
b10001 J
b1 .
b1 B
b1 K
0#
b10 =
b10 ;
b10 <
b0 1
b10001 )
b10001 H
1:
b1000 3
b100000000100010000000000000010 5
b100000000100010000000000000010 E
#3830
b10 *
b10 I
b10 +
#4000
0"
#4500
b10 .
b10 B
b10 K
1"
#4530
b101 C
b100000 (
b11000 2
b10100 ?
#4730
b11111111111111100100000000110000 (
b10110 -
b10010 0
b10010 J
b10110 .
b10110 B
b10110 K
b10 /
b10 L
1%
b110 =
b11111111111111111001000000000110 ;
b1001000000000110 <
b10010 1
b10000 )
b10000 H
b10001 ,
b10001 G
0:
b0 3
b10001100001001000000000110 5
b10001100001001000000000110 E
#4830
b0 *
b0 I
b0 +
#5000
0"
#5500
1"
#5530
b110 C
b11111111111111100100000000110100 (
b11100 2
b11000 ?
#5730
1'
b0 -
1#
0%
b11111111111111111100000010011100 (
b11110 0
b11110 J
b0 .
b0 B
b0 K
b0 /
b0 L
b100000 =
b11111111111111111111000000100000 ;
b1111000000100000 <
b11110 1
b10010 )
b10010 H
b0 ,
b0 G
b100101111000000100000 5
b100101111000000100000 E
#6000
0"
#6500
1"
#6530
b111 C
b11111111111111111100000010100000 (
b100000 2
b11100 ?
#6730
b11 -
b101100 (
b10001 0
b10001 J
b10 .
b10 B
b10 K
0#
b11 =
b11 ;
b11 <
b0 1
b10001 )
b10001 H
1:
b1000 3
b100000000100010000000000000011 5
b100000000100010000000000000011 E
#6830
b11 *
b11 I
b11 +
#7000
0"
#7500
b11 .
b11 B
b11 K
1"
#7530
b1000 C
b110000 (
b100100 2
b100000 ?
#7730
b11111111111111100100000000111100 (
b10110 -
b10010 0
b10010 J
b10110 .
b10110 B
b10110 K
b11 /
b11 L
1%
b110 =
b11111111111111111001000000000110 ;
b1001000000000110 <
b10010 1
b10000 )
b10000 H
b10001 ,
b10001 G
0:
b0 3
b10001100001001000000000110 5
b10001100001001000000000110 E
#7830
b0 *
b0 I
b0 +
#8000
0"
#8500
1"
#8530
b1001 C
b11111111111111100100000001000000 (
b101000 2
b100100 ?
#8730
1'
b0 -
1#
0%
b11111111111111111100000010101000 (
b11110 0
b11110 J
b0 .
b0 B
b0 K
b0 /
b0 L
b100000 =
b11111111111111111111000000100000 ;
b1111000000100000 <
b11110 1
b10010 )
b10010 H
b0 ,
b0 G
b100101111000000100000 5
b100101111000000100000 E
#9000
0"
#9500
1"
#9530
b1010 C
b11111111111111111100000010101100 (
b101100 2
b101000 ?
#9730
x'
bx -
x&
bx (
bx 0
bx J
bx .
bx B
bx K
bx /
bx L
x#
x$
x%
b0x00000000x000000000000000x0xx0 *
b0x00000000x000000000000000x0xx0 I
bx =
bx ;
bx <
bx 1
bx )
bx H
bx ,
bx G
x:
x7
x6
x9
x8
bx 3
bx 5
bx E
#9830
bx @
bx *
bx I
bx +
